falcon_helpers/__init__.py
falcon_helpers/app.py
falcon_helpers/config.py
falcon_helpers/utils.py
falcon_helpers/contrib/__init__.py
falcon_helpers/contrib/auth.py
falcon_helpers/contrib/cli.py
falcon_helpers/contrib/logging.py
falcon_helpers/contrib/storage.py
falcon_helpers/contrib/wsgi.py
falcon_helpers/middlewares/__init__.py
falcon_helpers/middlewares/auth_required.py
falcon_helpers/middlewares/jinja2.py
falcon_helpers/middlewares/load_user.py
falcon_helpers/middlewares/marshmallow.py
falcon_helpers/middlewares/multi.py
falcon_helpers/middlewares/multipart.py
falcon_helpers/middlewares/parsejwt.py
falcon_helpers/middlewares/sqla.py
falcon_helpers/plugins/__init__.py
falcon_helpers/plugins/sentry.py
falcon_helpers/plugins/sqla.py
falcon_helpers/plugins/auth0/__init__.py
falcon_helpers/plugins/auth0/plugin.py
falcon_helpers/plugins/auth0/templates/login.html
falcon_helpers/resources/__init__.py
falcon_helpers/resources/auth0.py
falcon_helpers/resources/crud.py
falcon_helpers/resources/redirect.py
falcon_helpers/sqla/__init__.py
falcon_helpers/sqla/columns.py
falcon_helpers/sqla/core.py
falcon_helpers/sqla/db.py
falcon_helpers/sqla/orm.py
falcon_helpers/sqla/postgres.py
falcon_helpers/sqla/sqlite.py
falcon_helpers/sqla/utils.py
falcon_helpers/testing/__init__.py
falcon_helpers/testing/multipart.py
falcon_helpers/tests/__init__.py
falcon_helpers/tests/conftest.py
falcon_helpers/tests/fixtures.py
falcon_helpers/tests/test_app.py
falcon_helpers/tests/test_config.py
falcon_helpers/tests/files/keys/testkey
falcon_helpers/tests/files/keys/testkey.pub
falcon_helpers/tests/test_contrib/__init__.py
falcon_helpers/tests/test_contrib/test_auth.py
falcon_helpers/tests/test_contrib/test_cli.py
falcon_helpers/tests/test_contrib/test_logging.py
falcon_helpers/tests/test_contrib/test_storage.py
falcon_helpers/tests/test_middlewares/__init__.py
falcon_helpers/tests/test_middlewares/test_marshmallow.py
falcon_helpers/tests/test_middlewares/test_multi_middleware.py
falcon_helpers-0.21.1.dist-info/licenses/LICENSE
falcon_helpers-0.21.1.dist-info/METADATA
falcon_helpers-0.21.1.dist-info/WHEEL
falcon_helpers-0.21.1.dist-info/top_level.txt
falcon_helpers-0.21.1.dist-info/zip-safe
falcon_helpers-0.21.1.dist-info/RECORD
