Metadata-Version: 2.4
Name: falcon-helpers
Version: 0.21.1
Summary: A few helpful tools to make working with the falcon framework a real joy!
Home-page: https://github.com/level12/falcon-helpers
Author: Nick Zaccardi
Author-email: nicholas.zaccardi@gmail.com
License: BSD
Classifier: Intended Audience :: Developers
Classifier: License :: OSI Approved :: BSD License
Classifier: Operating System :: OS Independent
Classifier: Programming Language :: Python :: 3
Classifier: Programming Language :: Python :: 3.9
Classifier: Programming Language :: Python :: 3.10
License-File: LICENSE
Requires-Dist: cryptography
Requires-Dist: falcon==3.*
Requires-Dist: falcon_multipart
Requires-Dist: jinja2
Requires-Dist: marshmallow>=3
Requires-Dist: marshmallow-sqlalchemy
Requires-Dist: pyjwt>=2.4
Requires-Dist: sqlalchemy>=2
Requires-Dist: requests
Requires-Dist: ujson
Requires-Dist: wrapt
Provides-Extra: s3
Requires-Dist: boto3; extra == "s3"
Provides-Extra: cli
Requires-Dist: click; extra == "cli"
Provides-Extra: dev
Requires-Dist: moto; extra == "dev"
Requires-Dist: click; extra == "dev"
Requires-Dist: pytest>4; extra == "dev"
Requires-Dist: raven; extra == "dev"
Dynamic: author
Dynamic: author-email
Dynamic: classifier
Dynamic: description
Dynamic: home-page
Dynamic: license
Dynamic: license-file
Dynamic: provides-extra
Dynamic: requires-dist
Dynamic: summary
